drf_rules/__about__.py
drf_rules/__init__.py
drf_rules/permissions.py
drf_rules/py.typed
drf_rules-0.0.8.dist-info/METADATA
drf_rules-0.0.8.dist-info/WHEEL
drf_rules-0.0.8.dist-info/licenses/LICENSE
drf_rules-0.0.8.dist-info/licenses/LICENSE.txt
drf_rules-0.0.8.dist-info/RECORD
